zfstui/__init__.py
zfstui/dialogs.py
zfstui/helptext.py
zfstui/widgets.py
zfstui/zfs.py
zfstui-0.1.1.data/scripts/zfstui
zfstui-0.1.1.dist-info/LICENSE
zfstui-0.1.1.dist-info/METADATA
zfstui-0.1.1.dist-info/WHEEL
zfstui-0.1.1.dist-info/top_level.txt
zfstui-0.1.1.dist-info/RECORD
